LICENSE.txt
README.md
setup.cfg
setup.py
height_selection_sim/__init__.py
height_selection_sim/__main__.py
height_selection_sim.egg-info/PKG-INFO
height_selection_sim.egg-info/SOURCES.txt
height_selection_sim.egg-info/dependency_links.txt
height_selection_sim.egg-info/entry_points.txt
height_selection_sim.egg-info/requires.txt
height_selection_sim.egg-info/top_level.txt